ctapointing/__init__.py
ctapointing/camera/__init__.py
ctapointing/camera/distortion.py
ctapointing/camera/pointingcamera.py
ctapointing/camera/sciencecamera.py
ctapointing/camera/utils.py
ctapointing/camera/tests/__init__.py
ctapointing/camera/tests/test_camera.py
ctapointing/camera/tests/test_cameraconfig.py
ctapointing/camera/tests/test_distortion.py
ctapointing/camera/tests/test_sciencecamera.py
ctapointing/camera/tests/transformed_distortion.txt
ctapointing/catalog/__init__.py
ctapointing/catalog/bsc5.dat
ctapointing/catalog/gaia_catalog.py
ctapointing/catalog/utils.py
ctapointing/catalog/tests/__init__.py
ctapointing/config/__init__.py
ctapointing/config/config.py
ctapointing/config/traits.py
ctapointing/config/tests/test_config.py
ctapointing/config/tests/test_traits.py
ctapointing/coordinates/__init__.py
ctapointing/coordinates/sciencecamera_frame.py
ctapointing/coordinates/skycamera_frame.py
ctapointing/coordinates/utils.py
ctapointing/coordinates/tests/__init__.py
ctapointing/coordinates/tests/test_skycameraframe.py
ctapointing/data/images/simulated/ZWO_2600/Polaris/ctapointing_simulation_0a0375d7-e6ba-45ed-b47d-09291ff2493d.fits.gz
ctapointing/data/images/simulated/ZWO_2600/Polaris/ctapointing_simulation_0a0375d7-e6ba-45ed-b47d-09291ff2493d.h5
ctapointing/data/masks/MAGIC_110718_ledmask.fits
ctapointing/data/masks/MAGIC_110718_mask.fits
ctapointing/data/masks/MST_MAGIC_combined_mask_2019_50mm.fits
ctapointing/data/masks/MST_MAGIC_combined_sourcemask_50mm.fits
ctapointing/data/masks/MST_mask_2019_50mm.fits
ctapointing/data/masks/MST_mask_ZWO_50mm.fits
ctapointing/data/masks/MST_mask_ZWO_50mm_2deg_tolerance.fits
ctapointing/data/masks/MST_mask_ZWO_50mm_2deg_tolerance.xcf
ctapointing/data/masks/MST_mask_ZWO_50mm_ledmask.fits
ctapointing/database/__init__.py
ctapointing/database/configuration.py
ctapointing/database/mongodb.py
ctapointing/database/mongodbtableio.py
ctapointing/database/tests/__init__.py
ctapointing/database/tests/read_images.py
ctapointing-0.6.4.dist-info/licenses/LICENSE
ctapointing-0.6.4.dist-info/METADATA
ctapointing-0.6.4.dist-info/WHEEL
ctapointing-0.6.4.dist-info/entry_points.txt
ctapointing-0.6.4.dist-info/top_level.txt
ctapointing-0.6.4.dist-info/RECORD
