Metadata-Version: 2.4
Name: ctapointing
Version: 0.6.4
Summary: Offline MST telescope pointing pipeline prototype for CTA (the Cherenkov Telescope Array)
Author: Christopher van Eldik
Author-email: christopher.van.eldik@fau.de
Maintainer-email: Christopher van Eldik <christopher.van.eldik@fau.de>
License: BSD-3-Clause
Project-URL: repository, https://gitlab.com/vaneldik/ctapointing
Project-URL: documentation, https://ctapointing.readthedocs.io
Classifier: Intended Audience :: Science/Research
Classifier: License :: OSI Approved :: BSD License
Classifier: Programming Language :: Python :: 3
Classifier: Programming Language :: Python :: 3.10
Classifier: Programming Language :: Python :: 3.11
Classifier: Programming Language :: Python :: 3.12
Classifier: Programming Language :: Python :: Implementation :: CPython
Classifier: Topic :: Scientific/Engineering :: Astronomy
Classifier: Development Status :: 3 - Alpha
Requires-Python: >=3.10
License-File: LICENSE
Requires-Dist: ctapipe
Requires-Dist: astropy
Requires-Dist: scipy
Requires-Dist: numpy
Requires-Dist: matplotlib
Requires-Dist: astroquery
Requires-Dist: pymongo
Requires-Dist: scikit-image
Requires-Dist: sep
Requires-Dist: iminuit
Provides-Extra: docs
Requires-Dist: sphinx; extra == "docs"
Requires-Dist: sphinx_rtd_theme; extra == "docs"
Requires-Dist: sphinx-automodapi; extra == "docs"
Requires-Dist: numpydoc; extra == "docs"
Requires-Dist: matplotlib; extra == "docs"
Dynamic: license-file
